{
 "first": {
  "price": "6000000.00",
  "number": [
   {
    "round": 1,
    "value": "221609"
   }
  ]
 },
 "third": {
  "price": "80000.00",
  "number": [
   {
    "round": 6,
    "value": "008405"
   },
   {
    "round": 4,
    "value": "227654"
   },
   {
    "round": 10,
    "value": "316039"
   },
   {
    "round": 5,
    "value": "451750"
   },
   {
    "round": 8,
    "value": "461353"
   },
   {
    "round": 1,
    "value": "561762"
   },
   {
    "round": 9,
    "value": "571349"
   },
   {
    "round": 3,
    "value": "588645"
   },
   {
    "round": 7,
    "value": "639778"
   },
   {
    "round": 2,
    "value": "867284"
   }
  ]
 },
 "fourth": {
  "price": "40000.00",
  "number": [
   {
    "round": 49,
    "value": "029853"
   },
   {
    "round": 21,
    "value": "030930"
   },
   {
    "round": 27,
    "value": "031982"
   },
   {
    "round": 42,
    "value": "045238"
   },
   {
    "round": 30,
    "value": "061422"
   },
   {
    "round": 2,
    "value": "066115"
   },
   {
    "round": 8,
    "value": "103182"
   },
   {
    "round": 33,
    "value": "111672"
   },
   {
    "round": 7,
    "value": "117709"
   },
   {
    "round": 28,
    "value": "138544"
   },
   {
    "round": 22,
    "value": "181377"
   },
   {
    "round": 40,
    "value": "184697"
   },
   {
    "round": 12,
    "value": "228660"
   },
   {
    "round": 45,
    "value": "239990"
   },
   {
    "round": 50,
    "value": "242378"
   },
   {
    "round": 36,
    "value": "254534"
   },
   {
    "round": 38,
    "value": "263316"
   },
   {
    "round": 11,
    "value": "266652"
   },
   {
    "round": 29,
    "value": "268646"
   },
   {
    "round": 18,
    "value": "280445"
   },
   {
    "round": 24,
    "value": "308239"
   },
   {
    "round": 44,
    "value": "324718"
   },
   {
    "round": 19,
    "value": "345527"
   },
   {
    "round": 17,
    "value": "346230"
   },
   {
    "round": 39,
    "value": "348451"
   },
   {
    "round": 35,
    "value": "373009"
   },
   {
    "round": 9,
    "value": "380460"
   },
   {
    "round": 37,
    "value": "380575"
   },
   {
    "round": 48,
    "value": "383503"
   },
   {
    "round": 34,
    "value": "391208"
   },
   {
    "round": 47,
    "value": "401563"
   },
   {
    "round": 26,
    "value": "431528"
   },
   {
    "round": 6,
    "value": "432519"
   },
   {
    "round": 13,
    "value": "486317"
   },
   {
    "round": 10,
    "value": "518079"
   },
   {
    "round": 31,
    "value": "524983"
   },
   {
    "round": 32,
    "value": "585691"
   },
   {
    "round": 4,
    "value": "600222"
   },
   {
    "round": 20,
    "value": "626828"
   },
   {
    "round": 25,
    "value": "636141"
   },
   {
    "round": 5,
    "value": "640547"
   },
   {
    "round": 46,
    "value": "655773"
   },
   {
    "round": 14,
    "value": "663555"
   },
   {
    "round": 43,
    "value": "694772"
   },
   {
    "round": 3,
    "value": "794419"
   },
   {
    "round": 23,
    "value": "818909"
   },
   {
    "round": 15,
    "value": "847058"
   },
   {
    "round": 41,
    "value": "890278"
   },
   {
    "round": 1,
    "value": "928266"
   },
   {
    "round": 16,
    "value": "971812"
   }
  ]
 },
 "fifth": {
  "price": "20000.00",
  "number": [
   {
    "round": 96,
    "value": "017009"
   },
   {
    "round": 10,
    "value": "018263"
   },
   {
    "round": 8,
    "value": "019447"
   },
   {
    "round": 56,
    "value": "025606"
   },
   {
    "round": 90,
    "value": "032810"
   },
   {
    "round": 31,
    "value": "033302"
   },
   {
    "round": 71,
    "value": "048327"
   },
   {
    "round": 83,
    "value": "064599"
   },
   {
    "round": 15,
    "value": "085134"
   },
   {
    "round": 62,
    "value": "103701"
   },
   {
    "round": 94,
    "value": "120814"
   },
   {
    "round": 22,
    "value": "130509"
   },
   {
    "round": 21,
    "value": "143019"
   },
   {
    "round": 76,
    "value": "159188"
   },
   {
    "round": 72,
    "value": "161188"
   },
   {
    "round": 50,
    "value": "170589"
   },
   {
    "round": 4,
    "value": "188020"
   },
   {
    "round": 89,
    "value": "196476"
   },
   {
    "round": 100,
    "value": "222176"
   },
   {
    "round": 63,
    "value": "224211"
   },
   {
    "round": 7,
    "value": "236502"
   },
   {
    "round": 48,
    "value": "242778"
   },
   {
    "round": 44,
    "value": "266660"
   },
   {
    "round": 91,
    "value": "276566"
   },
   {
    "round": 99,
    "value": "286282"
   },
   {
    "round": 41,
    "value": "290263"
   },
   {
    "round": 23,
    "value": "296740"
   },
   {
    "round": 84,
    "value": "297166"
   },
   {
    "round": 14,
    "value": "298216"
   },
   {
    "round": 66,
    "value": "298662"
   },
   {
    "round": 86,
    "value": "300322"
   },
   {
    "round": 58,
    "value": "300672"
   },
   {
    "round": 40,
    "value": "333445"
   },
   {
    "round": 46,
    "value": "335216"
   },
   {
    "round": 68,
    "value": "335740"
   },
   {
    "round": 42,
    "value": "355744"
   },
   {
    "round": 98,
    "value": "366463"
   },
   {
    "round": 61,
    "value": "378023"
   },
   {
    "round": 73,
    "value": "392057"
   },
   {
    "round": 34,
    "value": "409830"
   },
   {
    "round": 33,
    "value": "415430"
   },
   {
    "round": 67,
    "value": "421506"
   },
   {
    "round": 64,
    "value": "432960"
   },
   {
    "round": 74,
    "value": "434094"
   },
   {
    "round": 69,
    "value": "470991"
   },
   {
    "round": 59,
    "value": "479783"
   },
   {
    "round": 38,
    "value": "480586"
   },
   {
    "round": 57,
    "value": "483991"
   },
   {
    "round": 9,
    "value": "487396"
   },
   {
    "round": 65,
    "value": "505119"
   },
   {
    "round": 19,
    "value": "506898"
   },
   {
    "round": 75,
    "value": "510709"
   },
   {
    "round": 37,
    "value": "526178"
   },
   {
    "round": 52,
    "value": "527062"
   },
   {
    "round": 25,
    "value": "539373"
   },
   {
    "round": 20,
    "value": "550987"
   },
   {
    "round": 27,
    "value": "568726"
   },
   {
    "round": 49,
    "value": "582132"
   },
   {
    "round": 16,
    "value": "589676"
   },
   {
    "round": 43,
    "value": "604044"
   },
   {
    "round": 92,
    "value": "606922"
   },
   {
    "round": 79,
    "value": "611833"
   },
   {
    "round": 17,
    "value": "612417"
   },
   {
    "round": 26,
    "value": "622035"
   },
   {
    "round": 93,
    "value": "623443"
   },
   {
    "round": 39,
    "value": "626668"
   },
   {
    "round": 32,
    "value": "627314"
   },
   {
    "round": 36,
    "value": "635693"
   },
   {
    "round": 30,
    "value": "642758"
   },
   {
    "round": 81,
    "value": "646757"
   },
   {
    "round": 29,
    "value": "673704"
   },
   {
    "round": 82,
    "value": "676731"
   },
   {
    "round": 77,
    "value": "680340"
   },
   {
    "round": 2,
    "value": "694501"
   },
   {
    "round": 88,
    "value": "695652"
   },
   {
    "round": 28,
    "value": "707937"
   },
   {
    "round": 3,
    "value": "739187"
   },
   {
    "round": 97,
    "value": "740820"
   },
   {
    "round": 53,
    "value": "779839"
   },
   {
    "round": 54,
    "value": "788753"
   },
   {
    "round": 6,
    "value": "790451"
   },
   {
    "round": 24,
    "value": "797257"
   },
   {
    "round": 60,
    "value": "807492"
   },
   {
    "round": 78,
    "value": "819420"
   },
   {
    "round": 12,
    "value": "821046"
   },
   {
    "round": 13,
    "value": "831078"
   },
   {
    "round": 70,
    "value": "836607"
   },
   {
    "round": 55,
    "value": "849065"
   },
   {
    "round": 18,
    "value": "850489"
   },
   {
    "round": 80,
    "value": "851057"
   },
   {
    "round": 11,
    "value": "876529"
   },
   {
    "round": 51,
    "value": "881686"
   },
   {
    "round": 87,
    "value": "918457"
   },
   {
    "round": 5,
    "value": "929430"
   },
   {
    "round": 35,
    "value": "930975"
   },
   {
    "round": 47,
    "value": "958570"
   },
   {
    "round": 95,
    "value": "963318"
   },
   {
    "round": 85,
    "value": "964703"
   },
   {
    "round": 45,
    "value": "976549"
   },
   {
    "round": 1,
    "value": "990463"
   }
  ]
 },
 "last2": {
  "price": "2000.00",
  "number": [
   {
    "round": 1,
    "value": "87"
   }
  ]
 },
 "last3b": {
  "price": "4000.00",
  "number": [
   {
    "round": 1,
    "value": "507"
   },
   {
    "round": 2,
    "value": "523"
   }
  ]
 },
 "second": {
  "price": "200000.00",
  "number": [
   {
    "round": 4,
    "value": "273392"
   },
   {
    "round": 1,
    "value": "399504"
   },
   {
    "round": 2,
    "value": "522824"
   },
   {
    "round": 5,
    "value": "525913"
   },
   {
    "round": 3,
    "value": "532412"
   }
  ]
 },
 "last3f": {
  "price": "4000.00",
  "number": [
   {
    "round": 2,
    "value": "008"
   },
   {
    "round": 1,
    "value": "228"
   }
  ]
 },
 "near1": {
  "price": "100000.00",
  "number": [
   {
    "round": 1,
    "value": "221608"
   },
   {
    "round": 2,
    "value": "221610"
   }
  ]
 }
}