{
 "first": {
  "price": "6000000.00",
  "number": [
   {
    "round": 1,
    "value": "077258"
   }
  ]
 },
 "third": {
  "price": "80000.00",
  "number": [
   {
    "round": 6,
    "value": "062798"
   },
   {
    "round": 7,
    "value": "071808"
   },
   {
    "round": 8,
    "value": "137779"
   },
   {
    "round": 3,
    "value": "141265"
   },
   {
    "round": 1,
    "value": "205386"
   },
   {
    "round": 5,
    "value": "236522"
   },
   {
    "round": 2,
    "value": "344379"
   },
   {
    "round": 10,
    "value": "376897"
   },
   {
    "round": 9,
    "value": "678273"
   },
   {
    "round": 4,
    "value": "889372"
   }
  ]
 },
 "fourth": {
  "price": "40000.00",
  "number": [
   {
    "round": 19,
    "value": "004969"
   },
   {
    "round": 37,
    "value": "049201"
   },
   {
    "round": 27,
    "value": "071318"
   },
   {
    "round": 42,
    "value": "087044"
   },
   {
    "round": 34,
    "value": "117488"
   },
   {
    "round": 23,
    "value": "126096"
   },
   {
    "round": 24,
    "value": "138203"
   },
   {
    "round": 2,
    "value": "149268"
   },
   {
    "round": 6,
    "value": "179517"
   },
   {
    "round": 4,
    "value": "181287"
   },
   {
    "round": 15,
    "value": "183684"
   },
   {
    "round": 33,
    "value": "221359"
   },
   {
    "round": 47,
    "value": "235426"
   },
   {
    "round": 12,
    "value": "239271"
   },
   {
    "round": 40,
    "value": "241706"
   },
   {
    "round": 9,
    "value": "267661"
   },
   {
    "round": 21,
    "value": "343651"
   },
   {
    "round": 31,
    "value": "383667"
   },
   {
    "round": 5,
    "value": "398158"
   },
   {
    "round": 18,
    "value": "406890"
   },
   {
    "round": 22,
    "value": "424100"
   },
   {
    "round": 7,
    "value": "462939"
   },
   {
    "round": 10,
    "value": "499894"
   },
   {
    "round": 1,
    "value": "512115"
   },
   {
    "round": 11,
    "value": "524517"
   },
   {
    "round": 38,
    "value": "549070"
   },
   {
    "round": 50,
    "value": "595084"
   },
   {
    "round": 13,
    "value": "607591"
   },
   {
    "round": 14,
    "value": "610231"
   },
   {
    "round": 25,
    "value": "611485"
   },
   {
    "round": 29,
    "value": "661675"
   },
   {
    "round": 32,
    "value": "676765"
   },
   {
    "round": 20,
    "value": "689815"
   },
   {
    "round": 44,
    "value": "746831"
   },
   {
    "round": 30,
    "value": "751933"
   },
   {
    "round": 17,
    "value": "807187"
   },
   {
    "round": 43,
    "value": "819551"
   },
   {
    "round": 8,
    "value": "822365"
   },
   {
    "round": 39,
    "value": "831441"
   },
   {
    "round": 48,
    "value": "838473"
   },
   {
    "round": 16,
    "value": "844778"
   },
   {
    "round": 26,
    "value": "846552"
   },
   {
    "round": 28,
    "value": "872200"
   },
   {
    "round": 45,
    "value": "904216"
   },
   {
    "round": 46,
    "value": "906309"
   },
   {
    "round": 49,
    "value": "933186"
   },
   {
    "round": 41,
    "value": "954486"
   },
   {
    "round": 36,
    "value": "959502"
   },
   {
    "round": 3,
    "value": "962421"
   },
   {
    "round": 35,
    "value": "981544"
   }
  ]
 },
 "fifth": {
  "price": "20000.00",
  "number": [
   {
    "round": 99,
    "value": "002645"
   },
   {
    "round": 72,
    "value": "009279"
   },
   {
    "round": 43,
    "value": "013358"
   },
   {
    "round": 41,
    "value": "022867"
   },
   {
    "round": 81,
    "value": "027867"
   },
   {
    "round": 69,
    "value": "048630"
   },
   {
    "round": 98,
    "value": "048902"
   },
   {
    "round": 23,
    "value": "066625"
   },
   {
    "round": 90,
    "value": "070570"
   },
   {
    "round": 3,
    "value": "087638"
   },
   {
    "round": 70,
    "value": "098401"
   },
   {
    "round": 7,
    "value": "117090"
   },
   {
    "round": 93,
    "value": "128859"
   },
   {
    "round": 47,
    "value": "150857"
   },
   {
    "round": 20,
    "value": "150884"
   },
   {
    "round": 52,
    "value": "157423"
   },
   {
    "round": 13,
    "value": "159736"
   },
   {
    "round": 48,
    "value": "166142"
   },
   {
    "round": 73,
    "value": "176069"
   },
   {
    "round": 71,
    "value": "178842"
   },
   {
    "round": 28,
    "value": "181425"
   },
   {
    "round": 96,
    "value": "185397"
   },
   {
    "round": 31,
    "value": "198321"
   },
   {
    "round": 1,
    "value": "209742"
   },
   {
    "round": 10,
    "value": "211232"
   },
   {
    "round": 11,
    "value": "212569"
   },
   {
    "round": 6,
    "value": "230557"
   },
   {
    "round": 38,
    "value": "233560"
   },
   {
    "round": 9,
    "value": "235288"
   },
   {
    "round": 88,
    "value": "255128"
   },
   {
    "round": 86,
    "value": "255713"
   },
   {
    "round": 87,
    "value": "281959"
   },
   {
    "round": 37,
    "value": "286897"
   },
   {
    "round": 42,
    "value": "301010"
   },
   {
    "round": 89,
    "value": "303443"
   },
   {
    "round": 74,
    "value": "311928"
   },
   {
    "round": 85,
    "value": "312569"
   },
   {
    "round": 67,
    "value": "325100"
   },
   {
    "round": 15,
    "value": "349878"
   },
   {
    "round": 29,
    "value": "359349"
   },
   {
    "round": 77,
    "value": "377914"
   },
   {
    "round": 26,
    "value": "391193"
   },
   {
    "round": 55,
    "value": "400024"
   },
   {
    "round": 84,
    "value": "404129"
   },
   {
    "round": 82,
    "value": "420034"
   },
   {
    "round": 63,
    "value": "449276"
   },
   {
    "round": 54,
    "value": "468767"
   },
   {
    "round": 64,
    "value": "486230"
   },
   {
    "round": 34,
    "value": "489085"
   },
   {
    "round": 92,
    "value": "504459"
   },
   {
    "round": 59,
    "value": "517755"
   },
   {
    "round": 36,
    "value": "528568"
   },
   {
    "round": 53,
    "value": "539926"
   },
   {
    "round": 25,
    "value": "541367"
   },
   {
    "round": 61,
    "value": "541964"
   },
   {
    "round": 16,
    "value": "552949"
   },
   {
    "round": 17,
    "value": "557731"
   },
   {
    "round": 45,
    "value": "558121"
   },
   {
    "round": 19,
    "value": "558969"
   },
   {
    "round": 30,
    "value": "566060"
   },
   {
    "round": 14,
    "value": "571790"
   },
   {
    "round": 94,
    "value": "586755"
   },
   {
    "round": 62,
    "value": "594323"
   },
   {
    "round": 91,
    "value": "612528"
   },
   {
    "round": 80,
    "value": "613164"
   },
   {
    "round": 32,
    "value": "614441"
   },
   {
    "round": 97,
    "value": "630890"
   },
   {
    "round": 79,
    "value": "632846"
   },
   {
    "round": 33,
    "value": "644887"
   },
   {
    "round": 95,
    "value": "657807"
   },
   {
    "round": 78,
    "value": "662364"
   },
   {
    "round": 83,
    "value": "668596"
   },
   {
    "round": 57,
    "value": "682249"
   },
   {
    "round": 22,
    "value": "684331"
   },
   {
    "round": 50,
    "value": "699170"
   },
   {
    "round": 66,
    "value": "710561"
   },
   {
    "round": 100,
    "value": "712440"
   },
   {
    "round": 65,
    "value": "714337"
   },
   {
    "round": 18,
    "value": "736353"
   },
   {
    "round": 35,
    "value": "782849"
   },
   {
    "round": 27,
    "value": "829641"
   },
   {
    "round": 40,
    "value": "830365"
   },
   {
    "round": 51,
    "value": "841669"
   },
   {
    "round": 68,
    "value": "855212"
   },
   {
    "round": 2,
    "value": "887997"
   },
   {
    "round": 39,
    "value": "891331"
   },
   {
    "round": 8,
    "value": "893452"
   },
   {
    "round": 5,
    "value": "906950"
   },
   {
    "round": 12,
    "value": "907056"
   },
   {
    "round": 76,
    "value": "908632"
   },
   {
    "round": 60,
    "value": "909583"
   },
   {
    "round": 56,
    "value": "920033"
   },
   {
    "round": 75,
    "value": "921332"
   },
   {
    "round": 4,
    "value": "935364"
   },
   {
    "round": 46,
    "value": "952217"
   },
   {
    "round": 24,
    "value": "981604"
   },
   {
    "round": 49,
    "value": "988451"
   },
   {
    "round": 21,
    "value": "988878"
   },
   {
    "round": 44,
    "value": "991050"
   },
   {
    "round": 58,
    "value": "992960"
   }
  ]
 },
 "last2": {
  "price": "2000.00",
  "number": [
   {
    "round": 1,
    "value": "82"
   }
  ]
 },
 "last3b": {
  "price": "4000.00",
  "number": [
   {
    "round": 2,
    "value": "401"
   },
   {
    "round": 1,
    "value": "485"
   }
  ]
 },
 "second": {
  "price": "200000.00",
  "number": [
   {
    "round": 5,
    "value": "082736"
   },
   {
    "round": 1,
    "value": "303780"
   },
   {
    "round": 4,
    "value": "425815"
   },
   {
    "round": 3,
    "value": "813107"
   },
   {
    "round": 2,
    "value": "953223"
   }
  ]
 },
 "last3f": {
  "price": "4000.00",
  "number": [
   {
    "round": 2,
    "value": "739"
   },
   {
    "round": 1,
    "value": "740"
   }
  ]
 },
 "near1": {
  "price": "100000.00",
  "number": [
   {
    "round": 1,
    "value": "077257"
   },
   {
    "round": 2,
    "value": "077259"
   }
  ]
 }
}